{
    "name": null,
    "frequency_range": null,
    "allow_gain": false,
    "nonlinear_spec": null,
    "type": "PoleResidue",
    "eps_inf": 2.2790089684064383,
    "poles": [
        [
            {
                "real": -43751953634059.84,
                "imag": -268915664122832.22
            },
            {
                "real": -48672282479623.3,
                "imag": 47631491149701.805
            }
        ],
        [
            {
                "real": -12864163707073.557,
                "imag": -212715265015293.47
            },
            {
                "real": 9629432527961.828,
                "imag": 32446525673387.023
            }
        ],
        [
            {
                "real": -8554883765996.891,
                "imag": -197304528437893.94
            },
            {
                "real": -63539247250542.96,
                "imag": 47623484398511.67
            }
        ],
        [
            {
                "real": -8039944470121.809,
                "imag": -187705288345054.4
            },
            {
                "real": 42927001669849.97,
                "imag": -11308249698637.97
            }
        ],
        [
            {
                "real": -5905041920382.551,
                "imag": -18701597667854.293
            },
            {
                "real": -3116179133790.155,
                "imag": 1756380180968476.8
            }
        ],
        [
            {
                "real": -34949498395535.938,
                "imag": -146096032312516.34
            },
            {
                "real": -507216576561841.6,
                "imag": -105367317367756.89
            }
        ],
        [
            {
                "real": -8972819446385.342,
                "imag": -81514739071877.5
            },
            {
                "real": 11561089138867.338,
                "imag": 194186179802876.94
            }
        ],
        [
            {
                "real": -35207268904298.47,
                "imag": -120228927649361.55
            },
            {
                "real": 595642236361616.1,
                "imag": 18911403519673.473
            }
        ]
    ]
}